{
  "meta": {
    "title": "WCUP 通過タイムライン",
    "edition": "2026 北中米",
    "advancePerGroup": 2,
    "advanceBestThirds": 8,
    "points": { "win": 3, "draw": 1, "loss": 0 },
    "utcOffset": -4,
    "dataLastUpdated": "2026-06-29",
    "source": "https://en.wikipedia.org/wiki/2026_FIFA_World_Cup_knockout_stage",
    "disclaimer": "2026年北中米大会（48カ国・12組）の非公式可視化です。グループステージは全12組消化済み、現在は決勝トーナメント（R32）進行中につき、消化済みの試合のみ実スコアを反映しています（残りは未消化）。"
  },
  "teams": [
    { "id": "mex", "name": "メキシコ", "nameEn": "Mexico", "group": "A", "flag": "🇲🇽", "fifaRank": 14 },
    { "id": "kor", "name": "韓国", "nameEn": "South Korea", "group": "A", "flag": "🇰🇷", "fifaRank": 25 },
    { "id": "rsa", "name": "南アフリカ", "nameEn": "South Africa", "group": "A", "flag": "🇿🇦", "fifaRank": 60 },
    { "id": "cze", "name": "チェコ", "nameEn": "Czechia", "group": "A", "flag": "🇨🇿", "fifaRank": 40 },

    { "id": "can", "name": "カナダ", "nameEn": "Canada", "group": "B", "flag": "🇨🇦", "fifaRank": 30 },
    { "id": "sui", "name": "スイス", "nameEn": "Switzerland", "group": "B", "flag": "🇨🇭", "fifaRank": 19 },
    { "id": "qat", "name": "カタール", "nameEn": "Qatar", "group": "B", "flag": "🇶🇦", "fifaRank": 56 },
    { "id": "bih", "name": "ボスニア・ヘルツェゴビナ", "nameEn": "Bosnia and Herzegovina", "group": "B", "flag": "🇧🇦", "fifaRank": 64 },

    { "id": "bra", "name": "ブラジル", "nameEn": "Brazil", "group": "C", "flag": "🇧🇷", "fifaRank": 6 },
    { "id": "mar", "name": "モロッコ", "nameEn": "Morocco", "group": "C", "flag": "🇲🇦", "fifaRank": 7 },
    { "id": "sco", "name": "スコットランド", "nameEn": "Scotland", "group": "C", "flag": "🏴󠁧󠁢󠁳󠁣󠁴󠁿", "fifaRank": 42 },
    { "id": "hai", "name": "ハイチ", "nameEn": "Haiti", "group": "C", "flag": "🇭🇹", "fifaRank": 83 },

    { "id": "usa", "name": "アメリカ", "nameEn": "United States", "group": "D", "flag": "🇺🇸", "fifaRank": 17 },
    { "id": "par", "name": "パラグアイ", "nameEn": "Paraguay", "group": "D", "flag": "🇵🇾", "fifaRank": 41 },
    { "id": "aus", "name": "オーストラリア", "nameEn": "Australia", "group": "D", "flag": "🇦🇺", "fifaRank": 27 },
    { "id": "tur", "name": "トルコ", "nameEn": "Türkiye", "group": "D", "flag": "🇹🇷", "fifaRank": 22 },

    { "id": "ger", "name": "ドイツ", "nameEn": "Germany", "group": "E", "flag": "🇩🇪", "fifaRank": 10 },
    { "id": "ecu", "name": "エクアドル", "nameEn": "Ecuador", "group": "E", "flag": "🇪🇨", "fifaRank": 23 },
    { "id": "civ", "name": "コートジボワール", "nameEn": "Ivory Coast", "group": "E", "flag": "🇨🇮", "fifaRank": 33 },
    { "id": "cuw", "name": "キュラソー", "nameEn": "Curaçao", "group": "E", "flag": "🇨🇼", "fifaRank": 82 },

    { "id": "ned", "name": "オランダ", "nameEn": "Netherlands", "group": "F", "flag": "🇳🇱", "fifaRank": 8 },
    { "id": "jpn", "name": "日本", "nameEn": "Japan", "group": "F", "flag": "🇯🇵", "fifaRank": 18 },
    { "id": "tun", "name": "チュニジア", "nameEn": "Tunisia", "group": "F", "flag": "🇹🇳", "fifaRank": 45 },
    { "id": "swe", "name": "スウェーデン", "nameEn": "Sweden", "group": "F", "flag": "🇸🇪", "fifaRank": 38 },

    { "id": "bel", "name": "ベルギー", "nameEn": "Belgium", "group": "G", "flag": "🇧🇪", "fifaRank": 9 },
    { "id": "irn", "name": "イラン", "nameEn": "Iran", "group": "G", "flag": "🇮🇷", "fifaRank": 20 },
    { "id": "egy", "name": "エジプト", "nameEn": "Egypt", "group": "G", "flag": "🇪🇬", "fifaRank": 29 },
    { "id": "nzl", "name": "ニュージーランド", "nameEn": "New Zealand", "group": "G", "flag": "🇳🇿", "fifaRank": 85 },

    { "id": "esp", "name": "スペイン", "nameEn": "Spain", "group": "H", "flag": "🇪🇸", "fifaRank": 2 },
    { "id": "uru", "name": "ウルグアイ", "nameEn": "Uruguay", "group": "H", "flag": "🇺🇾", "fifaRank": 16 },
    { "id": "ksa", "name": "サウジアラビア", "nameEn": "Saudi Arabia", "group": "H", "flag": "🇸🇦", "fifaRank": 61 },
    { "id": "cpv", "name": "カーボベルデ", "nameEn": "Cape Verde", "group": "H", "flag": "🇨🇻", "fifaRank": 67 },

    { "id": "fra", "name": "フランス", "nameEn": "France", "group": "I", "flag": "🇫🇷", "fifaRank": 3 },
    { "id": "sen", "name": "セネガル", "nameEn": "Senegal", "group": "I", "flag": "🇸🇳", "fifaRank": 15 },
    { "id": "nor", "name": "ノルウェー", "nameEn": "Norway", "group": "I", "flag": "🇳🇴", "fifaRank": 31 },
    { "id": "irq", "name": "イラク", "nameEn": "Iraq", "group": "I", "flag": "🇮🇶", "fifaRank": 57 },

    { "id": "arg", "name": "アルゼンチン", "nameEn": "Argentina", "group": "J", "flag": "🇦🇷", "fifaRank": 1 },
    { "id": "aut", "name": "オーストリア", "nameEn": "Austria", "group": "J", "flag": "🇦🇹", "fifaRank": 24 },
    { "id": "alg", "name": "アルジェリア", "nameEn": "Algeria", "group": "J", "flag": "🇩🇿", "fifaRank": 28 },
    { "id": "jor", "name": "ヨルダン", "nameEn": "Jordan", "group": "J", "flag": "🇯🇴", "fifaRank": 63 },

    { "id": "por", "name": "ポルトガル", "nameEn": "Portugal", "group": "K", "flag": "🇵🇹", "fifaRank": 5 },
    { "id": "col", "name": "コロンビア", "nameEn": "Colombia", "group": "K", "flag": "🇨🇴", "fifaRank": 13 },
    { "id": "uzb", "name": "ウズベキスタン", "nameEn": "Uzbekistan", "group": "K", "flag": "🇺🇿", "fifaRank": 50 },
    { "id": "cod", "name": "コンゴ民主共和国", "nameEn": "DR Congo", "group": "K", "flag": "🇨🇩", "fifaRank": 46 },

    { "id": "eng", "name": "イングランド", "nameEn": "England", "group": "L", "flag": "🏴󠁧󠁢󠁥󠁮󠁧󠁿", "fifaRank": 4 },
    { "id": "cro", "name": "クロアチア", "nameEn": "Croatia", "group": "L", "flag": "🇭🇷", "fifaRank": 11 },
    { "id": "pan", "name": "パナマ", "nameEn": "Panama", "group": "L", "flag": "🇵🇦", "fifaRank": 34 },
    { "id": "gha", "name": "ガーナ", "nameEn": "Ghana", "group": "L", "flag": "🇬🇭", "fifaRank": 73 }
  ],
  "groups": [
    { "id": "A", "teamIds": ["mex", "kor", "rsa", "cze"] },
    { "id": "B", "teamIds": ["can", "sui", "qat", "bih"] },
    { "id": "C", "teamIds": ["bra", "mar", "sco", "hai"] },
    { "id": "D", "teamIds": ["usa", "par", "aus", "tur"] },
    { "id": "E", "teamIds": ["ger", "ecu", "civ", "cuw"] },
    { "id": "F", "teamIds": ["ned", "jpn", "tun", "swe"] },
    { "id": "G", "teamIds": ["bel", "irn", "egy", "nzl"] },
    { "id": "H", "teamIds": ["esp", "uru", "ksa", "cpv"] },
    { "id": "I", "teamIds": ["fra", "sen", "nor", "irq"] },
    { "id": "J", "teamIds": ["arg", "aut", "alg", "jor"] },
    { "id": "K", "teamIds": ["por", "col", "uzb", "cod"] },
    { "id": "L", "teamIds": ["eng", "cro", "pan", "gha"] }
  ],
  "matches": [
    { "id": "A-1", "group": "A", "matchday": 1, "kickoff": "2026-06-11T13:00", "tz": -6, "home": "mex", "away": "rsa", "score": { "home": 2, "away": 0 }, "goals": [ { "minute": 9, "side": "home", "player": "キニョネス" }, { "minute": 67, "side": "home", "player": "ヒメネス" } ] },
    { "id": "A-2", "group": "A", "matchday": 1, "kickoff": "2026-06-11T20:00", "tz": -6, "home": "kor", "away": "cze", "score": { "home": 2, "away": 1 }, "goals": [ { "minute": 59, "side": "away", "player": "クレイチー" }, { "minute": 67, "side": "home", "player": "ファン・インボム" }, { "minute": 80, "side": "home", "player": "オ・ヒョンギュ" } ] },
    { "id": "A-3", "group": "A", "matchday": 2, "kickoff": "2026-06-18T12:00", "home": "cze", "away": "rsa", "score": { "home": 1, "away": 1 }, "goals": [ { "minute": 6, "side": "home", "player": "サディレク" }, { "minute": 83, "side": "away", "player": "モコエナ(PK)" } ] },
    { "id": "A-4", "group": "A", "matchday": 2, "kickoff": "2026-06-18T19:00", "tz": -6, "home": "mex", "away": "kor", "score": { "home": 1, "away": 0 }, "goals": [ { "minute": 50, "side": "home", "player": "ロモ" } ] },
    { "id": "A-5", "group": "A", "matchday": 3, "kickoff": "2026-06-24T19:00", "tz": -6, "home": "cze", "away": "mex", "score": { "home": 0, "away": 3 }, "goals": [ { "minute": 55, "side": "away", "player": "チャベス" }, { "minute": 61, "side": "away", "player": "キニョネス" }, { "minute": 90, "plus": 4, "side": "away", "player": "フィダルゴ" } ] },
    { "id": "A-6", "group": "A", "matchday": 3, "kickoff": "2026-06-24T19:00", "tz": -6, "home": "rsa", "away": "kor", "score": { "home": 1, "away": 0 }, "goals": [ { "minute": 63, "side": "home", "player": "マセコ" } ] },

    { "id": "B-1", "group": "B", "matchday": 1, "kickoff": "2026-06-12T15:00", "home": "can", "away": "bih", "score": { "home": 1, "away": 1 }, "goals": [ { "minute": 21, "side": "away", "player": "ルキッチ" }, { "minute": 78, "side": "home", "player": "ラリン" } ] },
    { "id": "B-2", "group": "B", "matchday": 1, "kickoff": "2026-06-13T12:00", "tz": -7, "home": "qat", "away": "sui", "score": { "home": 1, "away": 1 }, "goals": [ { "minute": 17, "side": "away", "player": "エンボロ(PK)" }, { "minute": 90, "plus": 4, "side": "home", "player": "ムハイム(OG)" } ] },
    { "id": "B-3", "group": "B", "matchday": 2, "kickoff": "2026-06-18T12:00", "tz": -7, "home": "sui", "away": "bih", "score": { "home": 4, "away": 1 }, "goals": [ { "minute": 74, "side": "home", "player": "マンザンビ" }, { "minute": 84, "side": "home", "player": "バルガス" }, { "minute": 90, "side": "home", "player": "マンザンビ" }, { "minute": 90, "plus": 3, "side": "away", "player": "マフミッチ" }, { "minute": 90, "plus": 7, "side": "home", "player": "シャカ(PK)" } ] },
    { "id": "B-4", "group": "B", "matchday": 2, "kickoff": "2026-06-18T15:00", "tz": -7, "home": "can", "away": "qat", "score": { "home": 6, "away": 0 }, "goals": [ { "minute": 16, "side": "home", "player": "ラリン" }, { "minute": 29, "side": "home", "player": "ダビド" }, { "minute": 45, "plus": 3, "side": "home", "player": "ダビド" }, { "minute": 64, "side": "home", "player": "サリバ" }, { "minute": 75, "side": "home", "player": "マナイ(OG)" }, { "minute": 90, "plus": 2, "side": "home", "player": "ダビド" } ] },
    { "id": "B-5", "group": "B", "matchday": 3, "kickoff": "2026-06-24T12:00", "tz": -7, "home": "sui", "away": "can", "score": { "home": 2, "away": 1 }, "goals": [ { "minute": 46, "side": "home", "player": "バルガス" }, { "minute": 57, "side": "home", "player": "マンザンビ" }, { "minute": 76, "side": "away", "player": "ダビド" } ] },
    { "id": "B-6", "group": "B", "matchday": 3, "kickoff": "2026-06-24T12:00", "tz": -7, "home": "bih", "away": "qat", "score": { "home": 3, "away": 1 }, "goals": [ { "minute": 29, "side": "home", "player": "アライベゴビッチ" }, { "minute": 34, "side": "home", "player": "アブナダ(OG)" }, { "minute": 42, "side": "away", "player": "アル＝ハイドス" }, { "minute": 80, "side": "home", "player": "マフミッチ" } ] },

    { "id": "C-1", "group": "C", "matchday": 1, "kickoff": "2026-06-13T18:00", "home": "bra", "away": "mar", "score": { "home": 1, "away": 1 }, "goals": [ { "minute": 21, "side": "away", "player": "サイビリ" }, { "minute": 32, "side": "home", "player": "ヴィニシウス" } ] },
    { "id": "C-2", "group": "C", "matchday": 1, "kickoff": "2026-06-13T21:00", "home": "hai", "away": "sco", "score": { "home": 0, "away": 1 }, "goals": [ { "minute": 28, "side": "away", "player": "マッギン" } ] },
    { "id": "C-3", "group": "C", "matchday": 2, "kickoff": "2026-06-19T18:00", "home": "sco", "away": "mar", "score": { "home": 0, "away": 1 }, "goals": [ { "minute": 2, "side": "away", "player": "サイビリ" } ] },
    { "id": "C-4", "group": "C", "matchday": 2, "kickoff": "2026-06-19T20:30", "home": "bra", "away": "hai", "score": { "home": 3, "away": 0 }, "goals": [ { "minute": 23, "side": "home", "player": "クーニャ" }, { "minute": 36, "side": "home", "player": "クーニャ" }, { "minute": 45, "plus": 3, "side": "home", "player": "ヴィニシウス" } ] },
    { "id": "C-5", "group": "C", "matchday": 3, "kickoff": "2026-06-24T18:00", "home": "sco", "away": "bra", "score": { "home": 0, "away": 3 }, "goals": [ { "minute": 7, "side": "away", "player": "ヴィニシウス" }, { "minute": 45, "plus": 3, "side": "away", "player": "ヴィニシウス" }, { "minute": 60, "side": "away", "player": "クーニャ" } ] },
    { "id": "C-6", "group": "C", "matchday": 3, "kickoff": "2026-06-24T18:00", "home": "mar", "away": "hai", "score": { "home": 4, "away": 2 }, "goals": [ { "minute": 10, "side": "away", "player": "ブヌ(OG)" }, { "minute": 39, "side": "home", "player": "ハキミ" }, { "minute": 43, "side": "away", "player": "イシドル" }, { "minute": 45, "plus": 1, "side": "home", "player": "サイビリ" }, { "minute": 78, "side": "home", "player": "ラヒミ" }, { "minute": 89, "side": "home", "player": "ヤシン" } ] },

    { "id": "D-1", "group": "D", "matchday": 1, "kickoff": "2026-06-12T18:00", "tz": -7, "home": "usa", "away": "par", "score": { "home": 4, "away": 1 }, "goals": [ { "minute": 7, "side": "home", "player": "ボバディージャ(OG)" }, { "minute": 31, "side": "home", "player": "バログン" }, { "minute": 45, "plus": 5, "side": "home", "player": "バログン" }, { "minute": 73, "side": "away", "player": "マウリシオ" }, { "minute": 90, "plus": 8, "side": "home", "player": "レイナ" } ] },
    { "id": "D-2", "group": "D", "matchday": 1, "kickoff": "2026-06-13T21:00", "tz": -7, "home": "aus", "away": "tur", "score": { "home": 2, "away": 0 }, "goals": [ { "minute": 27, "side": "home", "player": "イランクンダ" }, { "minute": 75, "side": "home", "player": "メトカーフ" } ] },
    { "id": "D-3", "group": "D", "matchday": 2, "kickoff": "2026-06-19T12:00", "tz": -7, "home": "usa", "away": "aus", "score": { "home": 2, "away": 0 }, "goals": [ { "minute": 11, "side": "home", "player": "バージェス(OG)" }, { "minute": 43, "side": "home", "player": "フリーマン" } ] },
    { "id": "D-4", "group": "D", "matchday": 2, "kickoff": "2026-06-19T20:00", "tz": -7, "home": "tur", "away": "par", "score": { "home": 0, "away": 1 }, "goals": [ { "minute": 2, "side": "away", "player": "ガラルサ" } ] },
    { "id": "D-5", "group": "D", "matchday": 3, "kickoff": "2026-06-25T19:00", "tz": -7, "home": "tur", "away": "usa", "score": { "home": 3, "away": 2 }, "goals": [ { "minute": 3, "side": "away", "player": "トラスティ" }, { "minute": 10, "side": "home", "player": "ギュレル" }, { "minute": 31, "side": "home", "player": "ユルマズ" }, { "minute": 49, "side": "away", "player": "ベルハルター" }, { "minute": 90, "plus": 8, "side": "home", "player": "アイハン" } ] },
    { "id": "D-6", "group": "D", "matchday": 3, "kickoff": "2026-06-25T19:00", "tz": -7, "home": "par", "away": "aus", "score": { "home": 0, "away": 0 }, "goals": [] },

    { "id": "E-1", "group": "E", "matchday": 1, "kickoff": "2026-06-14T12:00", "tz": -5, "home": "ger", "away": "cuw", "score": { "home": 7, "away": 1 }, "goals": [ { "minute": 6, "side": "home", "player": "ンメチャ" }, { "minute": 21, "side": "away", "player": "コメネンシア" }, { "minute": 38, "side": "home", "player": "シュロッターベック" }, { "minute": 45, "plus": 5, "side": "home", "player": "ハベルツ(PK)" }, { "minute": 47, "side": "home", "player": "ムシアラ" }, { "minute": 68, "side": "home", "player": "ブラウン" }, { "minute": 78, "side": "home", "player": "ウンダフ" }, { "minute": 88, "side": "home", "player": "ハベルツ" } ] },
    { "id": "E-2", "group": "E", "matchday": 1, "kickoff": "2026-06-14T19:00", "home": "civ", "away": "ecu", "score": { "home": 1, "away": 0 }, "goals": [ { "minute": 90, "side": "home", "player": "ディアロ" } ] },
    { "id": "E-3", "group": "E", "matchday": 2, "kickoff": "2026-06-20T16:00", "home": "ger", "away": "civ", "score": { "home": 2, "away": 1 }, "goals": [ { "minute": 30, "side": "away", "player": "ケシエ" }, { "minute": 68, "side": "home", "player": "ウンダフ" }, { "minute": 90, "plus": 4, "side": "home", "player": "ウンダフ" } ] },
    { "id": "E-4", "group": "E", "matchday": 2, "kickoff": "2026-06-20T19:00", "tz": -5, "home": "ecu", "away": "cuw", "score": { "home": 0, "away": 0 }, "goals": [] },
    { "id": "E-5", "group": "E", "matchday": 3, "kickoff": "2026-06-25T16:00", "home": "cuw", "away": "civ", "score": { "home": 0, "away": 2 }, "goals": [ { "minute": 7, "side": "away", "player": "ペペ" }, { "minute": 64, "side": "away", "player": "ペペ" } ] },
    { "id": "E-6", "group": "E", "matchday": 3, "kickoff": "2026-06-25T16:00", "home": "ecu", "away": "ger", "score": { "home": 2, "away": 1 }, "goals": [ { "minute": 2, "side": "away", "player": "サネ" }, { "minute": 9, "side": "home", "player": "アングロ" }, { "minute": 77, "side": "home", "player": "プラタ" } ] },

    { "id": "F-1", "group": "F", "matchday": 1, "kickoff": "2026-06-14T15:00", "tz": -5, "home": "ned", "away": "jpn", "score": { "home": 2, "away": 2 }, "goals": [ { "minute": 50, "side": "home", "player": "ファン・ダイク" }, { "minute": 57, "side": "away", "player": "中村敬斗" }, { "minute": 64, "side": "home", "player": "サマービル" }, { "minute": 88, "side": "away", "player": "鎌田大地" } ] },
    { "id": "F-2", "group": "F", "matchday": 1, "kickoff": "2026-06-14T20:00", "tz": -6, "home": "swe", "away": "tun", "score": { "home": 5, "away": 1 }, "goals": [ { "minute": 7, "side": "home", "player": "アヤリ" }, { "minute": 30, "side": "home", "player": "イサク" }, { "minute": 43, "side": "away", "player": "レキク" }, { "minute": 59, "side": "home", "player": "ヨケレス" }, { "minute": 84, "side": "home", "player": "スバンベリ" }, { "minute": 90, "plus": 6, "side": "home", "player": "アヤリ" } ] },
    { "id": "F-3", "group": "F", "matchday": 2, "kickoff": "2026-06-20T12:00", "tz": -5, "home": "ned", "away": "swe", "score": { "home": 5, "away": 1 }, "goals": [ { "minute": 5, "side": "home", "player": "ブロビー" }, { "minute": 17, "side": "home", "player": "ブロビー" }, { "minute": 47, "side": "home", "player": "ガクポ" }, { "minute": 54, "side": "home", "player": "ガクポ" }, { "minute": 59, "side": "away", "player": "エランガ" }, { "minute": 89, "side": "home", "player": "サマービル" } ] },
    { "id": "F-4", "group": "F", "matchday": 2, "kickoff": "2026-06-20T22:00", "tz": -6, "home": "tun", "away": "jpn", "score": { "home": 0, "away": 4 }, "goals": [ { "minute": 4, "side": "away", "player": "鎌田大地" }, { "minute": 31, "side": "away", "player": "上田綺世" }, { "minute": 69, "side": "away", "player": "伊東純也" }, { "minute": 83, "side": "away", "player": "上田綺世" } ] },
    { "id": "F-5", "group": "F", "matchday": 3, "kickoff": "2026-06-25T18:00", "tz": -5, "home": "jpn", "away": "swe", "score": { "home": 1, "away": 1 }, "goals": [ { "minute": 56, "side": "home", "player": "前田大然" }, { "minute": 62, "side": "away", "player": "エランガ" } ] },
    { "id": "F-6", "group": "F", "matchday": 3, "kickoff": "2026-06-25T18:00", "tz": -5, "home": "tun", "away": "ned", "score": { "home": 1, "away": 3 }, "goals": [ { "minute": 3, "side": "away", "player": "スキリ(OG)" }, { "minute": 7, "side": "away", "player": "ブロビー" }, { "minute": 54, "side": "home", "player": "マストゥーリ" }, { "minute": 62, "side": "away", "player": "ファン・ヘッケ" } ] },

    { "id": "G-1", "group": "G", "matchday": 1, "kickoff": "2026-06-15T12:00", "tz": -7, "home": "bel", "away": "egy", "score": { "home": 1, "away": 1 }, "goals": [ { "minute": 19, "side": "away", "player": "アシュール" }, { "minute": 66, "side": "home", "player": "ハニー(OG)" } ] },
    { "id": "G-2", "group": "G", "matchday": 1, "kickoff": "2026-06-15T18:00", "tz": -7, "home": "irn", "away": "nzl", "score": { "home": 2, "away": 2 }, "goals": [ { "minute": 7, "side": "away", "player": "ジャスト" }, { "minute": 32, "side": "home", "player": "レザイアン" }, { "minute": 54, "side": "away", "player": "ジャスト" }, { "minute": 64, "side": "home", "player": "モヘビ" } ] },
    { "id": "G-3", "group": "G", "matchday": 2, "kickoff": "2026-06-21T12:00", "tz": -7, "home": "bel", "away": "irn", "score": { "home": 0, "away": 0 }, "goals": [] },
    { "id": "G-4", "group": "G", "matchday": 2, "kickoff": "2026-06-21T18:00", "tz": -7, "home": "nzl", "away": "egy", "score": { "home": 1, "away": 3 }, "goals": [ { "minute": 15, "side": "home", "player": "サーマン" }, { "minute": 58, "side": "away", "player": "ジコ" }, { "minute": 67, "side": "away", "player": "サラー" }, { "minute": 82, "side": "away", "player": "トレゼゲ" } ] },
    { "id": "G-5", "group": "G", "matchday": 3, "kickoff": "2026-06-26T20:00", "tz": -7, "home": "egy", "away": "irn", "score": { "home": 1, "away": 1 }, "goals": [ { "minute": 5, "side": "home", "player": "サベル" }, { "minute": 14, "side": "away", "player": "レザイアン" } ] },
    { "id": "G-6", "group": "G", "matchday": 3, "kickoff": "2026-06-26T20:00", "tz": -7, "home": "nzl", "away": "bel", "score": { "home": 1, "away": 5 }, "goals": [ { "minute": 28, "side": "away", "player": "トロサール" }, { "minute": 50, "side": "away", "player": "トロサール" }, { "minute": 66, "side": "away", "player": "デ・ブライネ" }, { "minute": 84, "side": "home", "player": "ジャスト" }, { "minute": 86, "side": "away", "player": "ルカク" }, { "minute": 90, "plus": 4, "side": "away", "player": "サレマーケルス" } ] },

    { "id": "H-1", "group": "H", "matchday": 1, "kickoff": "2026-06-15T12:00", "home": "esp", "away": "cpv", "score": { "home": 0, "away": 0 }, "goals": [] },
    { "id": "H-2", "group": "H", "matchday": 1, "kickoff": "2026-06-15T18:00", "home": "ksa", "away": "uru", "score": { "home": 1, "away": 1 }, "goals": [ { "minute": 41, "side": "home", "player": "アル＝アムリ" }, { "minute": 80, "side": "away", "player": "アラウホ" } ] },
    { "id": "H-3", "group": "H", "matchday": 2, "kickoff": "2026-06-21T12:00", "home": "esp", "away": "ksa", "score": { "home": 4, "away": 0 }, "goals": [ { "minute": 10, "side": "home", "player": "ヤマル" }, { "minute": 21, "side": "home", "player": "オヤルサバル" }, { "minute": 24, "side": "home", "player": "オヤルサバル" }, { "minute": 49, "side": "home", "player": "アル＝タンバクティ(OG)" } ] },
    { "id": "H-4", "group": "H", "matchday": 2, "kickoff": "2026-06-21T18:00", "home": "uru", "away": "cpv", "score": { "home": 2, "away": 2 }, "goals": [ { "minute": 21, "side": "away", "player": "ピナ" }, { "minute": 44, "side": "home", "player": "アラウホ" }, { "minute": 45, "plus": 6, "side": "home", "player": "カノビオ" }, { "minute": 61, "side": "away", "player": "バレラ" } ] },
    { "id": "H-5", "group": "H", "matchday": 3, "kickoff": "2026-06-26T19:00", "tz": -5, "home": "cpv", "away": "ksa", "score": { "home": 0, "away": 0 }, "goals": [] },
    { "id": "H-6", "group": "H", "matchday": 3, "kickoff": "2026-06-26T18:00", "tz": -6, "home": "uru", "away": "esp", "score": { "home": 0, "away": 1 }, "goals": [ { "minute": 42, "side": "away", "player": "バエナ" } ] },

    { "id": "I-1", "group": "I", "matchday": 1, "kickoff": "2026-06-16T15:00", "home": "fra", "away": "sen", "score": { "home": 3, "away": 1 }, "goals": [ { "minute": 66, "side": "home", "player": "ムバッペ" }, { "minute": 82, "side": "home", "player": "バルコラ" }, { "minute": 90, "plus": 5, "side": "away", "player": "ンバイェ" }, { "minute": 90, "plus": 6, "side": "home", "player": "ムバッペ" } ] },
    { "id": "I-2", "group": "I", "matchday": 1, "kickoff": "2026-06-16T18:00", "home": "irq", "away": "nor", "score": { "home": 1, "away": 4 }, "goals": [ { "minute": 29, "side": "away", "player": "ハーランド" }, { "minute": 39, "side": "home", "player": "フセイン" }, { "minute": 43, "side": "away", "player": "ハーランド" }, { "minute": 76, "side": "away", "player": "オスティゴール" }, { "minute": 90, "plus": 6, "side": "away", "player": "フセイン(OG)" } ] },
    { "id": "I-3", "group": "I", "matchday": 2, "kickoff": "2026-06-22T17:00", "home": "fra", "away": "irq", "score": { "home": 3, "away": 0 }, "goals": [ { "minute": 14, "side": "home", "player": "ムバッペ" }, { "minute": 54, "side": "home", "player": "ムバッペ" }, { "minute": 66, "side": "home", "player": "デンベレ" } ] },
    { "id": "I-4", "group": "I", "matchday": 2, "kickoff": "2026-06-22T20:00", "home": "nor", "away": "sen", "score": { "home": 3, "away": 2 }, "goals": [ { "minute": 43, "side": "home", "player": "ペデルセン" }, { "minute": 48, "side": "home", "player": "ハーランド" }, { "minute": 53, "side": "away", "player": "サール" }, { "minute": 58, "side": "home", "player": "ハーランド" }, { "minute": 90, "plus": 3, "side": "away", "player": "サール" } ] },
    { "id": "I-5", "group": "I", "matchday": 3, "kickoff": "2026-06-26T15:00", "home": "nor", "away": "fra", "score": { "home": 1, "away": 4 }, "goals": [ { "minute": 7, "side": "away", "player": "デンベレ" }, { "minute": 20, "side": "away", "player": "デンベレ" }, { "minute": 21, "side": "home", "player": "オースゴール" }, { "minute": 32, "side": "away", "player": "デンベレ" }, { "minute": 90, "plus": 4, "side": "away", "player": "ドゥエ" } ] },
    { "id": "I-6", "group": "I", "matchday": 3, "kickoff": "2026-06-26T15:00", "home": "sen", "away": "irq", "score": { "home": 5, "away": 0 }, "goals": [ { "minute": 4, "side": "home", "player": "ディアラ" }, { "minute": 56, "side": "home", "player": "サール" }, { "minute": 59, "side": "home", "player": "ゲイエ" }, { "minute": 71, "side": "home", "player": "ゲイエ" }, { "minute": 82, "side": "home", "player": "ンディアイエ" } ] },

    { "id": "J-1", "group": "J", "matchday": 1, "kickoff": "2026-06-16T20:00", "tz": -5, "home": "arg", "away": "alg", "score": { "home": 3, "away": 0 }, "goals": [ { "minute": 17, "side": "home", "player": "メッシ" }, { "minute": 60, "side": "home", "player": "メッシ" }, { "minute": 76, "side": "home", "player": "メッシ" } ] },
    { "id": "J-2", "group": "J", "matchday": 1, "kickoff": "2026-06-16T21:00", "tz": -7, "home": "aut", "away": "jor", "score": { "home": 3, "away": 1 }, "goals": [ { "minute": 21, "side": "home", "player": "シュミット" }, { "minute": 50, "side": "away", "player": "オルワン" }, { "minute": 77, "side": "home", "player": "アル＝アラブ(OG)" }, { "minute": 90, "plus": 12, "side": "home", "player": "アルナウトビッチ(PK)" } ] },
    { "id": "J-3", "group": "J", "matchday": 2, "kickoff": "2026-06-22T12:00", "tz": -5, "home": "arg", "away": "aut", "score": { "home": 2, "away": 0 }, "goals": [ { "minute": 38, "side": "home", "player": "メッシ" }, { "minute": 90, "plus": 5, "side": "home", "player": "メッシ" } ] },
    { "id": "J-4", "group": "J", "matchday": 2, "kickoff": "2026-06-22T20:00", "tz": -7, "home": "jor", "away": "alg", "score": { "home": 1, "away": 2 }, "goals": [ { "minute": 36, "side": "home", "player": "アル＝ラシュダン" }, { "minute": 69, "side": "away", "player": "ベンブアリ" }, { "minute": 82, "side": "away", "player": "グイリ" } ] },
    { "id": "J-5", "group": "J", "matchday": 3, "kickoff": "2026-06-27T21:00", "tz": -5, "home": "alg", "away": "aut", "score": { "home": 3, "away": 3 }, "goals": [ { "minute": 28, "side": "away", "player": "アルナウトビッチ" }, { "minute": 45, "side": "home", "player": "ベルガリ" }, { "minute": 55, "side": "away", "player": "ザビッツァー" }, { "minute": 60, "side": "home", "player": "マフレズ" }, { "minute": 90, "plus": 3, "side": "home", "player": "マフレズ" }, { "minute": 90, "plus": 6, "side": "away", "player": "カライジッチ" } ] },
    { "id": "J-6", "group": "J", "matchday": 3, "kickoff": "2026-06-27T21:00", "tz": -5, "home": "jor", "away": "arg", "score": { "home": 1, "away": 3 }, "goals": [ { "minute": 19, "side": "away", "player": "ロ・セルソ" }, { "minute": 31, "side": "away", "player": "ラウタロ・マルティネス(PK)" }, { "minute": 55, "side": "home", "player": "アル＝タマリ" }, { "minute": 80, "side": "away", "player": "メッシ" } ] },

    { "id": "K-1", "group": "K", "matchday": 1, "kickoff": "2026-06-17T12:00", "tz": -5, "home": "por", "away": "cod", "score": { "home": 1, "away": 1 }, "goals": [ { "minute": 6, "side": "home", "player": "ネベス" }, { "minute": 45, "plus": 5, "side": "away", "player": "ウィッサ" } ] },
    { "id": "K-2", "group": "K", "matchday": 1, "kickoff": "2026-06-17T20:00", "tz": -6, "home": "uzb", "away": "col", "score": { "home": 1, "away": 3 }, "goals": [ { "minute": 40, "side": "away", "player": "ムニョス" }, { "minute": 60, "side": "home", "player": "ファイズラエフ" }, { "minute": 65, "side": "away", "player": "ディアス" }, { "minute": 90, "plus": 9, "side": "away", "player": "カンパス" } ] },
    { "id": "K-3", "group": "K", "matchday": 2, "kickoff": "2026-06-23T12:00", "tz": -5, "home": "por", "away": "uzb", "score": { "home": 5, "away": 0 }, "goals": [ { "minute": 6, "side": "home", "player": "ロナウド" }, { "minute": 17, "side": "home", "player": "ヌノ・メンデス" }, { "minute": 39, "side": "home", "player": "ロナウド" }, { "minute": 60, "side": "home", "player": "ネマトフ(OG)" }, { "minute": 87, "side": "home", "player": "レオン" } ] },
    { "id": "K-4", "group": "K", "matchday": 2, "kickoff": "2026-06-23T20:00", "tz": -6, "home": "col", "away": "cod", "score": { "home": 1, "away": 0 }, "goals": [ { "minute": 76, "side": "home", "player": "ムニョス" } ] },
    { "id": "K-5", "group": "K", "matchday": 3, "kickoff": "2026-06-27T19:30", "home": "col", "away": "por", "score": { "home": 0, "away": 0 }, "goals": [] },
    { "id": "K-6", "group": "K", "matchday": 3, "kickoff": "2026-06-27T19:30", "home": "cod", "away": "uzb", "score": { "home": 3, "away": 1 }, "goals": [ { "minute": 10, "side": "away", "player": "ショムロドフ" }, { "minute": 68, "side": "home", "player": "ウィッサ(PK)" }, { "minute": 78, "side": "home", "player": "マイェレ" }, { "minute": 90, "plus": 1, "side": "home", "player": "ウィッサ" } ] },

    { "id": "L-1", "group": "L", "matchday": 1, "kickoff": "2026-06-17T15:00", "tz": -5, "home": "eng", "away": "cro", "score": { "home": 4, "away": 2 }, "goals": [ { "minute": 12, "side": "home", "player": "ケイン(PK)" }, { "minute": 36, "side": "away", "player": "バトゥリナ" }, { "minute": 42, "side": "home", "player": "ケイン" }, { "minute": 45, "plus": 5, "side": "away", "player": "ムサ" }, { "minute": 47, "side": "home", "player": "ベリンガム" }, { "minute": 85, "side": "home", "player": "ラッシュフォード" } ] },
    { "id": "L-2", "group": "L", "matchday": 1, "kickoff": "2026-06-17T19:00", "home": "gha", "away": "pan", "score": { "home": 1, "away": 0 }, "goals": [ { "minute": 90, "plus": 5, "side": "home", "player": "イレンキー" } ] },
    { "id": "L-3", "group": "L", "matchday": 2, "kickoff": "2026-06-23T16:00", "home": "eng", "away": "gha", "score": { "home": 0, "away": 0 }, "goals": [] },
    { "id": "L-4", "group": "L", "matchday": 2, "kickoff": "2026-06-23T19:00", "home": "pan", "away": "cro", "score": { "home": 0, "away": 1 }, "goals": [ { "minute": 54, "side": "away", "player": "ブディミル" } ] },
    { "id": "L-5", "group": "L", "matchday": 3, "kickoff": "2026-06-27T17:00", "home": "pan", "away": "eng", "score": { "home": 0, "away": 2 }, "goals": [ { "minute": 62, "side": "away", "player": "ベリンガム" }, { "minute": 67, "side": "away", "player": "ケイン" } ] },
    { "id": "L-6", "group": "L", "matchday": 3, "kickoff": "2026-06-27T17:00", "home": "cro", "away": "gha", "score": { "home": 2, "away": 1 }, "goals": [ { "minute": 31, "side": "home", "player": "スチッチ" }, { "minute": 73, "side": "away", "player": "ルカッセン" }, { "minute": 83, "side": "home", "player": "ヴラシッチ" } ] }
  ],
  "knockout": [
    { "round": "R32", "home": "rsa", "away": "can", "score": { "home": 0, "away": 1 }, "winner": "away", "goals": [ { "minute": 90, "plus": 2, "side": "away", "player": "ユースタキオ" } ] },
    { "round": "R32", "home": "bra", "away": "jpn", "score": { "home": 2, "away": 1 }, "winner": "home", "goals": [ { "minute": 29, "side": "away", "player": "佐野海舟" }, { "minute": 56, "side": "home", "player": "カゼミロ" }, { "minute": 90, "plus": 5, "side": "home", "player": "マルチネッリ" } ] },
    { "round": "R32", "home": "ger", "away": "par", "score": { "home": 1, "away": 1 }, "winner": "away", "shootout": { "home": 3, "away": 4 }, "goals": [ { "minute": 42, "side": "away", "player": "エンシソ" }, { "minute": 54, "side": "home", "player": "ハベルツ" } ] },
    { "round": "R32", "home": "ned", "away": "mar", "score": { "home": 1, "away": 1 }, "winner": "away", "shootout": { "home": 2, "away": 3 }, "goals": [ { "minute": 72, "side": "home", "player": "ガクポ" }, { "minute": 90, "plus": 1, "side": "away", "player": "ディオプ" } ] }
  ],
  "knockoutSchedule": [
    { "id": "73", "kickoff": "2026-06-28T12:00", "tz": -7 },
    { "id": "74", "kickoff": "2026-06-29T16:30", "third": "par" },
    { "id": "75", "kickoff": "2026-06-29T19:00", "tz": -6 },
    { "id": "76", "kickoff": "2026-06-29T12:00", "tz": -5 },
    { "id": "77", "kickoff": "2026-06-30T17:00", "third": "swe" },
    { "id": "78", "kickoff": "2026-06-30T12:00", "tz": -5 },
    { "id": "79", "kickoff": "2026-06-30T19:00", "tz": -6, "third": "ecu" },
    { "id": "80", "kickoff": "2026-07-01T12:00", "third": "cod" },
    { "id": "81", "kickoff": "2026-07-01T17:00", "tz": -7, "third": "bih" },
    { "id": "82", "kickoff": "2026-07-01T13:00", "tz": -7, "third": "sen" },
    { "id": "83", "kickoff": "2026-07-02T19:00" },
    { "id": "84", "kickoff": "2026-07-02T12:00", "tz": -7 },
    { "id": "85", "kickoff": "2026-07-02T20:00", "tz": -7, "third": "alg" },
    { "id": "86", "kickoff": "2026-07-03T18:00" },
    { "id": "87", "kickoff": "2026-07-03T20:30", "tz": -5, "third": "gha" },
    { "id": "88", "kickoff": "2026-07-03T13:00", "tz": -5 },
    { "id": "89", "kickoff": "2026-07-04T17:00" },
    { "id": "90", "kickoff": "2026-07-04T12:00", "tz": -5 },
    { "id": "91", "kickoff": "2026-07-05T16:00" },
    { "id": "92", "kickoff": "2026-07-05T18:00", "tz": -6 },
    { "id": "93", "kickoff": "2026-07-06T14:00", "tz": -5 },
    { "id": "94", "kickoff": "2026-07-06T17:00", "tz": -7 },
    { "id": "95", "kickoff": "2026-07-07T12:00" },
    { "id": "96", "kickoff": "2026-07-07T13:00", "tz": -7 },
    { "id": "97", "kickoff": "2026-07-09T16:00" },
    { "id": "98", "kickoff": "2026-07-10T12:00", "tz": -7 },
    { "id": "99", "kickoff": "2026-07-11T17:00" },
    { "id": "100", "kickoff": "2026-07-11T20:00", "tz": -5 },
    { "id": "101", "kickoff": "2026-07-14T14:00", "tz": -5 },
    { "id": "102", "kickoff": "2026-07-15T15:00" },
    { "id": "103", "kickoff": "2026-07-18T17:00" },
    { "id": "104", "kickoff": "2026-07-19T15:00" }
  ]
}
